pymodconf/__init__.py
pymodconf/io.py
pymodconf/parser.py
pymodconf/tag.py
tests/__init__.py
tests/test_io.py
tests/test_parser.py
tests/test_tag.py
pymodconf-0.0.3.dist-info/LICENSE
pymodconf-0.0.3.dist-info/METADATA
pymodconf-0.0.3.dist-info/WHEEL
pymodconf-0.0.3.dist-info/top_level.txt
pymodconf-0.0.3.dist-info/RECORD
