Metadata-Version: 2.1
Name: pymodconf
Version: 0.0.3
Summary: Modularized configuration files.
Home-page: UNKNOWN
Author: Lars Klitzke
Author-email: Lars.Klitzke@gmail.com
License: UNKNOWN
Platform: UNKNOWN
Classifier: Operating System :: OS Independent
Classifier: Programming Language :: Python :: 3.5
Classifier: Programming Language :: Python :: 3.6
Classifier: Programming Language :: Python :: 3.7
Classifier: License :: OSI Approved :: GNU Lesser General Public License v3 or later (LGPLv3+)
Classifier: Natural Language :: English
